{
  "generatedAt": "2026-03-10T01:42:00.067Z",
  "input": "D:\\Project\\merginer\\reports\\balance\\summary.csv",
  "rows": 30,
  "sampleMode": "phase1_lightweight",
  "interpretation": "directional",
  "overallStatus": "fail",
  "contentCycleStatus": "fail",
  "contentCycleChecks": {
    "midTierEntry": {
      "value": 0,
      "status": "fail"
    },
    "pairMissingDrop": {
      "value": 0.7571629873179897,
      "status": "pass"
    },
    "stagnationAbortTrend": {
      "value": 0,
      "status": "fail"
    },
    "weaponArmorCraftRatio": {
      "value": 0.9832116788321168,
      "status": "pass"
    },
    "conversionActivation": {
      "value": 0,
      "status": "fail",
      "mode": "diagnostic_only"
    },
    "clearRateTrend": {
      "value": 0,
      "mode": "trend_only"
    }
  },
  "checks": {
    "clearRate": {
      "value": 0,
      "status": "fail"
    },
    "abortedRate": {
      "value": 0,
      "status": "pass"
    },
    "logicalPlayTimeP50": {
      "value": 1209700,
      "status": "fail"
    },
    "logicalPlayTimeP90": {
      "value": 1215760,
      "status": "fail"
    },
    "weaponArmorCraftRatio": {
      "value": 0.9832116788321168,
      "status": "pass"
    },
    "steelMithrilCraftAvailability": {
      "value": {
        "craftSteel": 0,
        "craftMithril": 0
      },
      "status": "warn"
    },
    "enhanceRateDeltaTotal": {
      "value": 0.00026816018148745346,
      "status": "pass"
    },
    "enhanceRateDelta0to5": {
      "value": 0.00026816018148745346,
      "status": "pass"
    },
    "enhanceRateDelta6to9": {
      "value": 0,
      "status": "pass"
    },
    "enhanceRateDelta10plus": {
      "value": 0,
      "status": "pass"
    },
    "ironEfficiency": {
      "value": 0.9796967462989898,
      "status": "warn"
    },
    "steelEfficiency": {
      "value": 0,
      "status": "pass"
    },
    "mithrilEfficiency": {
      "value": 0,
      "status": "pass"
    }
  },
  "directionalChecks": {
    "craftBias": {
      "value": {
        "weaponArmorRatio": 0.9832116788321168,
        "armorLagMaxAvg": 14.933333333333334,
        "consecutiveWeaponCraftMaxAvg": 4.966666666666667
      },
      "status": "pass"
    },
    "conversionActivation": {
      "value": {
        "craftSteel": 0,
        "craftMithril": 0,
        "resourceConversionCount": 0
      },
      "status": "fail"
    },
    "midTierEntry": {
      "value": 0,
      "status": "fail"
    },
    "forgeProgress": {
      "value": 90,
      "status": "pass"
    },
    "tierResourceActivation": {
      "value": 0,
      "status": "fail"
    },
    "stagnationAbortRate": {
      "value": 1,
      "status": "fail"
    }
  },
  "decisionDiagnostics": {
    "conversionTopReasons": [
      {
        "reasonCode": "CONV_BLOCK_TARGET_ALREADY_MET",
        "count": 12052
      },
      {
        "reasonCode": "CONV_BLOCK_TARGET_NOT_ACTIVE",
        "count": 3840
      }
    ],
    "midTierTopReasons": [
      {
        "reasonCode": "ENHANCE_BLOCK_PAIR_NOT_FOUND",
        "count": 10340
      },
      {
        "reasonCode": "ENHANCE_BLOCK_MATERIAL_SHORTAGE",
        "count": 324
      }
    ]
  },
  "baselineComparison": {
    "baselineInput": "D:\\Project\\merginer\\reports\\balance\\verdict.baseline.json",
    "baselineLoaded": true,
    "baselinePairMissing": 42580,
    "baselineStagnationRate": 1
  },
  "boundaryProximity": {
    "clearRateNearPassWarnBoundary": false,
    "logicalPlayTimeP90NearWarnFailBoundary": false,
    "weaponArmorRatioDirectionalOnly": false
  },
  "secondaryCollectionTrigger": {
    "shouldRun": false,
    "reasons": [],
    "suggestedAdditionalSessionsPerPolicy": 25,
    "suggestedAdditionalTotalSessions": 75
  }
}